{"1":{"id":1,"name":"Northbridge","type":0,"parent_id":0,"address":"Building 1, 25, Aberdeen Street, Northbridge, Perth, Western Australia, 6000, Australia","mp_id":"address.2121005564981030","mp_lat":"-31.94802897","mp_lng":"115.86094053","created_at":"2020-07-21T02:35:00.000000Z","updated_at":"2020-07-21T02:35:00.000000Z","upload_id":null,"floor_id":null},"2":{"id":2,"name":"Leederville","type":0,"parent_id":0,"address":"A Block, Richmond Street, Leederville, Perth, Western Australia, 6007, Australia","mp_id":"address.3814715266816138","mp_lat":"-31.93396092","mp_lng":"115.84257784","created_at":"2020-07-21T02:35:00.000000Z","updated_at":"2020-07-21T02:35:00.000000Z","upload_id":null,"floor_id":null},"3":{"id":3,"name":"Building 2","type":1,"parent_id":1,"address":"Building 2, 30, Aberdeen Street, Northbridge, Perth, Western Australia, 6000, Australia","mp_id":"address.2121005564981030","mp_lat":"-31.94719248","mp_lng":"115.86127470","created_at":"2020-07-21T02:35:00.000000Z","updated_at":"2020-07-21T02:35:00.000000Z","upload_id":null,"floor_id":null},"6":{"id":6,"name":"Building 6","type":1,"parent_id":1,"address":"Building 6, 19, Aberdeen Street, Northbridge, Perth, Western Australia, 6000, Australia","mp_id":"address.2121005564981030","mp_lat":"-31.94845932","mp_lng":"115.86247545","created_at":"2020-07-21T02:35:00.000000Z","updated_at":"2020-07-21T02:35:00.000000Z","upload_id":null,"floor_id":null},"10":{"id":10,"name":"A Block","type":1,"parent_id":2,"address":"A Block, Richmond Street, Leederville, Perth, Western Australia, 6007, Australia","mp_id":"address.3814715266816138","mp_lat":"-31.93379349","mp_lng":"115.84181612","created_at":"2020-07-21T02:35:00.000000Z","updated_at":"2020-07-21T02:35:00.000000Z","upload_id":null,"floor_id":null},"14":{"id":14,"name":"B Block","type":1,"parent_id":2,"address":"B Block, Richmond Street, Leederville, Perth, Western Australia, 6007, Australia","mp_id":"address.3814715266816138","mp_lat":"-31.93418229","mp_lng":"115.84334853","created_at":"2020-07-21T02:35:00.000000Z","updated_at":"2020-07-21T02:35:00.000000Z","upload_id":null,"floor_id":null},"16":{"id":16,"name":"1-31-1","type":2,"parent_id":3,"address":"","mp_id":"","mp_lat":"-31.94685429","mp_lng":"115.86087930","created_at":"2020-07-21T02:35:00.000000Z","updated_at":"2020-10-30T01:44:36.000000Z","upload_id":null,"floor_id":1},"17":{"id":17,"name":"1-13","type":2,"parent_id":3,"address":"","mp_id":"","mp_lat":"-31.94692334","mp_lng":"115.86082099","created_at":"2020-07-21T02:35:00.000000Z","updated_at":"2020-10-30T01:45:21.000000Z","upload_id":null,"floor_id":1},"18":{"id":18,"name":"1-07","type":2,"parent_id":3,"address":"","mp_id":"","mp_lat":"-31.94701697","mp_lng":"115.86086572","created_at":"2020-07-21T02:35:00.000000Z","updated_at":"2020-10-30T01:46:04.000000Z","upload_id":null,"floor_id":1},"19":{"id":19,"name":"2-59","type":2,"parent_id":3,"address":"","mp_id":"","mp_lat":"-31.94703713","mp_lng":"115.86114023","created_at":"2020-07-21T02:35:00.000000Z","updated_at":"2020-10-30T01:46:44.000000Z","upload_id":null,"floor_id":2},"20":{"id":20,"name":"2-60","type":2,"parent_id":3,"address":"","mp_id":"","mp_lat":"-31.94700997","mp_lng":"115.86106702","created_at":"2020-07-21T02:35:00.000000Z","updated_at":"2020-10-30T01:47:29.000000Z","upload_id":null,"floor_id":2},"21":{"id":21,"name":"2-61","type":2,"parent_id":3,"address":"","mp_id":"","mp_lat":"-31.94698011","mp_lng":"115.86100541","created_at":"2020-07-21T02:35:00.000000Z","updated_at":"2020-10-30T01:48:26.000000Z","upload_id":null,"floor_id":2},"22":{"id":22,"name":"3-01","type":2,"parent_id":3,"address":"","mp_id":"","mp_lat":"-31.94728275","mp_lng":"115.86114450","created_at":"2020-07-21T02:35:00.000000Z","updated_at":"2020-10-30T01:49:10.000000Z","upload_id":null,"floor_id":3},"23":{"id":23,"name":"3-04","type":2,"parent_id":3,"address":"","mp_id":"","mp_lat":"-31.94723639","mp_lng":"115.86105334","created_at":"2020-07-21T02:35:00.000000Z","updated_at":"2020-10-30T01:49:54.000000Z","upload_id":null,"floor_id":3},"24":{"id":24,"name":"3-06","type":2,"parent_id":3,"address":"","mp_id":"","mp_lat":"-31.94719709","mp_lng":"115.86097629","created_at":"2020-07-21T02:35:00.000000Z","updated_at":"2020-10-30T01:50:33.000000Z","upload_id":null,"floor_id":3},"25":{"id":25,"name":"B116","type":2,"parent_id":6,"address":"","mp_id":"","mp_lat":null,"mp_lng":null,"created_at":"2020-07-21T02:35:00.000000Z","updated_at":"2020-07-21T02:35:00.000000Z","upload_id":null,"floor_id":null},"26":{"id":26,"name":"B133","type":2,"parent_id":6,"address":"","mp_id":"","mp_lat":null,"mp_lng":null,"created_at":"2020-07-21T02:35:00.000000Z","updated_at":"2020-07-21T02:35:00.000000Z","upload_id":null,"floor_id":null},"27":{"id":27,"name":"B110 Photography Studio","type":2,"parent_id":6,"address":"","mp_id":"","mp_lat":null,"mp_lng":null,"created_at":"2020-07-21T02:35:00.000000Z","updated_at":"2020-07-21T02:35:00.000000Z","upload_id":null,"floor_id":null},"28":{"id":28,"name":"B259","type":2,"parent_id":6,"address":"","mp_id":"","mp_lat":null,"mp_lng":null,"created_at":"2020-07-21T02:35:00.000000Z","updated_at":"2020-07-21T02:35:00.000000Z","upload_id":null,"floor_id":null},"29":{"id":29,"name":"B262","type":2,"parent_id":6,"address":"","mp_id":"","mp_lat":null,"mp_lng":null,"created_at":"2020-07-21T02:35:00.000000Z","updated_at":"2020-07-21T02:35:00.000000Z","upload_id":null,"floor_id":null},"30":{"id":30,"name":"B263","type":2,"parent_id":6,"address":"","mp_id":"","mp_lat":null,"mp_lng":null,"created_at":"2020-07-21T02:35:00.000000Z","updated_at":"2020-07-21T02:35:00.000000Z","upload_id":null,"floor_id":null},"31":{"id":31,"name":"B301","type":2,"parent_id":6,"address":"","mp_id":"","mp_lat":null,"mp_lng":null,"created_at":"2020-07-21T02:35:00.000000Z","updated_at":"2020-07-21T02:35:00.000000Z","upload_id":null,"floor_id":null},"32":{"id":32,"name":"B305","type":2,"parent_id":6,"address":"","mp_id":"","mp_lat":null,"mp_lng":null,"created_at":"2020-07-21T02:35:00.000000Z","updated_at":"2020-07-21T02:35:00.000000Z","upload_id":null,"floor_id":null},"33":{"id":33,"name":"B343","type":2,"parent_id":6,"address":"","mp_id":"","mp_lat":null,"mp_lng":null,"created_at":"2020-07-21T02:35:00.000000Z","updated_at":"2020-07-21T02:35:00.000000Z","upload_id":null,"floor_id":null},"34":{"id":34,"name":"B404","type":2,"parent_id":6,"address":"","mp_id":"","mp_lat":null,"mp_lng":null,"created_at":"2020-07-21T02:35:00.000000Z","updated_at":"2020-07-21T02:35:00.000000Z","upload_id":null,"floor_id":null},"35":{"id":35,"name":"B405","type":2,"parent_id":6,"address":"","mp_id":"","mp_lat":null,"mp_lng":null,"created_at":"2020-07-21T02:35:00.000000Z","updated_at":"2020-07-21T02:35:00.000000Z","upload_id":null,"floor_id":null},"36":{"id":36,"name":"Campus Cafe","type":2,"parent_id":10,"address":"","mp_id":"","mp_lat":"-31.93381496","mp_lng":"115.84181054","created_at":"2020-07-21T02:35:00.000000Z","updated_at":"2020-10-30T01:26:11.000000Z","upload_id":null,"floor_id":4},"37":{"id":37,"name":"A108","type":2,"parent_id":10,"address":"","mp_id":"","mp_lat":"-31.93373513","mp_lng":"115.84202541","created_at":"2020-07-21T02:35:00.000000Z","updated_at":"2020-10-30T01:27:48.000000Z","upload_id":null,"floor_id":4},"38":{"id":38,"name":"A140","type":2,"parent_id":10,"address":"","mp_id":"","mp_lat":"-31.93415381","mp_lng":"115.84214923","created_at":"2020-07-21T02:35:00.000000Z","updated_at":"2020-10-30T01:29:49.000000Z","upload_id":null,"floor_id":4},"39":{"id":39,"name":"A250 Lecture","type":2,"parent_id":10,"address":"","mp_id":"","mp_lat":"-31.93391517","mp_lng":"115.84177015","created_at":"2020-07-21T02:35:00.000000Z","updated_at":"2020-10-30T01:32:35.000000Z","upload_id":null,"floor_id":5},"40":{"id":40,"name":"A240 Library","type":2,"parent_id":10,"address":"","mp_id":"","mp_lat":"-31.93423115","mp_lng":"115.84164474","created_at":"2020-07-21T02:35:00.000000Z","updated_at":"2020-10-30T01:33:47.000000Z","upload_id":null,"floor_id":5},"41":{"id":41,"name":"A229","type":2,"parent_id":10,"address":"","mp_id":"","mp_lat":"-31.93378044","mp_lng":"115.84250329","created_at":"2020-07-21T02:35:00.000000Z","updated_at":"2020-10-30T01:31:14.000000Z","upload_id":null,"floor_id":5},"42":{"id":42,"name":"A319","type":2,"parent_id":10,"address":"","mp_id":"","mp_lat":"-31.93380839","mp_lng":"115.84163411","created_at":"2020-07-21T02:35:00.000000Z","updated_at":"2020-10-30T01:34:52.000000Z","upload_id":null,"floor_id":6},"43":{"id":43,"name":"A333","type":2,"parent_id":10,"address":"","mp_id":"","mp_lat":"-31.93418847","mp_lng":"115.84162868","created_at":"2020-07-21T02:35:00.000000Z","updated_at":"2020-10-30T01:35:52.000000Z","upload_id":null,"floor_id":6},"44":{"id":44,"name":"A346","type":2,"parent_id":10,"address":"","mp_id":"","mp_lat":"-31.93415562","mp_lng":"115.84222009","created_at":"2020-07-21T02:35:00.000000Z","updated_at":"2020-10-30T01:37:00.000000Z","upload_id":null,"floor_id":6},"45":{"id":45,"name":"A402","type":2,"parent_id":10,"address":"","mp_id":"","mp_lat":"-31.93379378","mp_lng":"115.84172197","created_at":"2020-07-21T02:35:00.000000Z","updated_at":"2020-10-30T01:38:06.000000Z","upload_id":null,"floor_id":7},"46":{"id":46,"name":"A413","type":2,"parent_id":10,"address":"","mp_id":"","mp_lat":"-31.93413270","mp_lng":"115.84172204","created_at":"2020-07-21T02:35:00.000000Z","updated_at":"2020-10-30T01:40:27.000000Z","upload_id":null,"floor_id":7},"47":{"id":47,"name":"A418","type":2,"parent_id":10,"address":"","mp_id":"","mp_lat":"-31.93418558","mp_lng":"115.84182797","created_at":"2020-07-21T02:35:00.000000Z","updated_at":"2020-10-30T01:41:48.000000Z","upload_id":null,"floor_id":7},"48":{"id":48,"name":"B102","type":2,"parent_id":14,"address":"","mp_id":"","mp_lat":null,"mp_lng":null,"created_at":"2020-07-21T02:35:00.000000Z","updated_at":"2020-07-21T02:35:00.000000Z","upload_id":null,"floor_id":null},"49":{"id":49,"name":"B103","type":2,"parent_id":14,"address":"","mp_id":"","mp_lat":null,"mp_lng":null,"created_at":"2020-07-21T02:35:00.000000Z","updated_at":"2020-07-21T02:35:00.000000Z","upload_id":null,"floor_id":null},"50":{"id":50,"name":"B107","type":2,"parent_id":14,"address":"","mp_id":"","mp_lat":null,"mp_lng":null,"created_at":"2020-07-21T02:35:00.000000Z","updated_at":"2020-07-21T02:35:00.000000Z","upload_id":null,"floor_id":null},"51":{"id":51,"name":"B220","type":2,"parent_id":14,"address":"","mp_id":"","mp_lat":null,"mp_lng":null,"created_at":"2020-07-21T02:35:00.000000Z","updated_at":"2020-07-21T02:35:00.000000Z","upload_id":null,"floor_id":null},"52":{"id":52,"name":"B221","type":2,"parent_id":14,"address":"","mp_id":"","mp_lat":null,"mp_lng":null,"created_at":"2020-07-21T02:35:00.000000Z","updated_at":"2020-07-21T02:35:00.000000Z","upload_id":null,"floor_id":null},"53":{"id":53,"name":"B227","type":2,"parent_id":14,"address":"","mp_id":"","mp_lat":null,"mp_lng":null,"created_at":"2020-07-21T02:35:00.000000Z","updated_at":"2020-07-21T02:35:00.000000Z","upload_id":null,"floor_id":null},"54":{"id":54,"name":"Balga","type":0,"parent_id":null,"address":"18 Loxwood Road, Balga Western Australia 6061, Australia","mp_id":"address.4949309105388658","mp_lat":"-31.86293982","mp_lng":"115.85375712","created_at":"2020-10-29T13:48:01.000000Z","updated_at":"2020-10-29T13:48:01.000000Z","upload_id":null,"floor_id":null},"55":{"id":55,"name":"East Perth","type":0,"parent_id":null,"address":"140 Royal Street, East Perth Western Australia 6004, Australia","mp_id":"address.247204199172092","mp_lat":"-31.95111200","mp_lng":"115.87215900","created_at":"2020-10-29T13:48:55.000000Z","updated_at":"2020-10-29T13:48:55.000000Z","upload_id":null,"floor_id":null},"56":{"id":56,"name":"Mount Lawley","type":0,"parent_id":null,"address":"North Metropolitan TAFE Mount Lawley, Harold Street, Perth, Western Australia 6050, Australia","mp_id":"poi.566935722277","mp_lat":"-31.93975300","mp_lng":"115.87564200","created_at":"2020-10-29T13:50:14.000000Z","updated_at":"2020-10-29T13:50:14.000000Z","upload_id":null,"floor_id":null},"57":{"id":57,"name":"Joondalup (McLarty)","type":0,"parent_id":null,"address":"North Metropolitan TAFE Joondalup (McLarty Avenue), 63 McLarty Avenue, Perth, Western Australia 6027, Australia","mp_id":"poi.180388681688","mp_lat":"-31.73866000","mp_lng":"115.76643000","created_at":"2020-10-29T13:53:42.000000Z","updated_at":"2020-10-29T13:53:42.000000Z","upload_id":null,"floor_id":null},"58":{"id":58,"name":"Joondalup (Kendrew)","type":0,"parent_id":null,"address":"North Metropolitan TAFE Joondalup (Kendrew Crescent), 35 Kendrew Crescent, Perth, Western Australia 6027, Australia","mp_id":"poi.8589944673","mp_lat":"-31.74782100","mp_lng":"115.77237800","created_at":"2020-10-29T13:54:44.000000Z","updated_at":"2020-10-29T13:54:44.000000Z","upload_id":null,"floor_id":null},"59":{"id":59,"name":"Midland","type":0,"parent_id":null,"address":"North Metropolitan TAFE Midland, Eddie Barron Dr., Perth, Western Australia 6056, Australia","mp_id":"poi.575525669725","mp_lat":"-31.87841800","mp_lng":"116.01916800","created_at":"2020-10-29T13:56:01.000000Z","updated_at":"2020-10-29T13:56:01.000000Z","upload_id":null,"floor_id":null},"60":{"id":60,"name":"Clarkson","type":0,"parent_id":null,"address":"North Metropolitan TAFE Clarkson, 31 Harmony Avenue, Perth, Western Australia 6030, Australia","mp_id":"poi.618475348798","mp_lat":"-31.67851000","mp_lng":"115.72608100","created_at":"2020-10-29T13:56:57.000000Z","updated_at":"2020-10-29T13:56:57.000000Z","upload_id":null,"floor_id":null},"61":{"id":61,"name":"Building 1","type":1,"parent_id":1,"address":"25 Aberdeen Street, Perth Western Australia 6000, Australia","mp_id":"address.2121005564981030","mp_lat":"-31.94806500","mp_lng":"115.86107600","created_at":"2020-10-30T01:55:21.000000Z","updated_at":"2020-10-30T01:55:21.000000Z","upload_id":null,"floor_id":null},"62":{"id":62,"name":"Building 3","type":1,"parent_id":1,"address":"14 Aberdeen Street, Perth Western Australia 6000, Australia","mp_id":"address.2121005564981030","mp_lat":"-31.94784100","mp_lng":"115.86251600","created_at":"2020-10-30T01:56:47.000000Z","updated_at":"2020-10-30T01:56:58.000000Z","upload_id":null,"floor_id":null},"63":{"id":63,"name":"Building 4","type":1,"parent_id":1,"address":"133 Newcastle Street, Perth Western Australia 6000, Australia","mp_id":"address.7135722327941750","mp_lat":"-31.94748000","mp_lng":"115.86315000","created_at":"2020-10-30T01:58:37.000000Z","updated_at":"2020-10-30T01:58:37.000000Z","upload_id":null,"floor_id":null},"64":{"id":64,"name":"C Block","type":1,"parent_id":2,"address":"82 Richmond Street, Leederville Western Australia 6007, Australia","mp_id":"address.3814715266816138","mp_lat":"-31.93397294","mp_lng":"115.84352962","created_at":"2020-10-30T01:58:38.000000Z","updated_at":"2020-10-30T01:58:38.000000Z","upload_id":null,"floor_id":null},"65":{"id":65,"name":"D Block","type":1,"parent_id":2,"address":"82 Richmond Street, Leederville Western Australia 6007, Australia","mp_id":"address.3814715266816138","mp_lat":"-31.93377087","mp_lng":"115.84348888","created_at":"2020-10-30T01:59:25.000000Z","updated_at":"2020-10-30T01:59:26.000000Z","upload_id":null,"floor_id":null},"66":{"id":66,"name":"Building 5","type":1,"parent_id":1,"address":"12 Aberdeen Street, Perth Western Australia 6000, Australia","mp_id":"address.2121005564981030","mp_lat":"-31.94827000","mp_lng":"115.86325600","created_at":"2020-10-30T01:59:29.000000Z","updated_at":"2020-10-30T01:59:29.000000Z","upload_id":null,"floor_id":null},"67":{"id":67,"name":"E Block","type":1,"parent_id":2,"address":"74 Richmond Street, Leederville Western Australia 6007, Australia","mp_id":"address.3814715266816138","mp_lat":"-31.93366806","mp_lng":"115.84404657","created_at":"2020-10-30T02:00:12.000000Z","updated_at":"2020-10-30T02:00:12.000000Z","upload_id":null,"floor_id":null},"68":{"id":68,"name":"Building 7","type":1,"parent_id":1,"address":"1 Museum Street, Perth Western Australia 6000, Australia","mp_id":"address.7388102856714716","mp_lat":"-31.94818608","mp_lng":"115.86157514","created_at":"2020-10-30T02:00:46.000000Z","updated_at":"2020-10-30T02:00:46.000000Z","upload_id":null,"floor_id":null},"69":{"id":69,"name":"F Block","type":1,"parent_id":2,"address":"43 Richmond Street, Leederville Western Australia 6007, Australia","mp_id":"address.3814715266816138","mp_lat":"-31.93459511","mp_lng":"115.84258208","created_at":"2020-10-30T02:01:18.000000Z","updated_at":"2020-10-30T02:01:18.000000Z","upload_id":null,"floor_id":null},"70":{"id":70,"name":"G Block","type":1,"parent_id":2,"address":"Oxford Yard, 196 Oxford St, Perth, Western Australia 6007, Australia","mp_id":"poi.695784733209","mp_lat":"-31.93455729","mp_lng":"115.84220852","created_at":"2020-10-30T02:01:43.000000Z","updated_at":"2020-10-30T02:01:43.000000Z","upload_id":null,"floor_id":null},"71":{"id":71,"name":"A101","type":2,"parent_id":10,"address":"","mp_id":"","mp_lat":"-31.93383901","mp_lng":"115.84223426","created_at":"2020-11-06T01:57:23.000000Z","updated_at":"2020-11-06T01:57:23.000000Z","upload_id":null,"floor_id":4},"72":{"id":72,"name":"A101B","type":2,"parent_id":10,"address":"","mp_id":"","mp_lat":"-31.93384972","mp_lng":"115.84214611","created_at":"2020-11-06T01:59:21.000000Z","updated_at":"2020-11-06T01:59:21.000000Z","upload_id":null,"floor_id":4},"73":{"id":73,"name":"A101D","type":2,"parent_id":10,"address":"","mp_id":"","mp_lat":"-31.93385371","mp_lng":"115.84206667","created_at":"2020-11-06T02:00:49.000000Z","updated_at":"2020-11-06T02:00:49.000000Z","upload_id":null,"floor_id":4},"74":{"id":74,"name":"A101E","type":2,"parent_id":10,"address":"","mp_id":"","mp_lat":"-31.93385125","mp_lng":"115.84199585","created_at":"2020-11-06T02:01:43.000000Z","updated_at":"2020-11-06T02:01:43.000000Z","upload_id":null,"floor_id":4},"75":{"id":75,"name":"A106","type":2,"parent_id":10,"address":"","mp_id":"","mp_lat":"-31.93384961","mp_lng":"115.84195786","created_at":"2020-11-06T02:03:20.000000Z","updated_at":"2020-11-06T02:03:20.000000Z","upload_id":null,"floor_id":4},"76":{"id":76,"name":"A123","type":2,"parent_id":10,"address":"","mp_id":"","mp_lat":"-31.93409869","mp_lng":"115.84161245","created_at":"2020-11-06T02:05:24.000000Z","updated_at":"2020-11-06T02:05:24.000000Z","upload_id":null,"floor_id":4},"77":{"id":77,"name":"A124","type":2,"parent_id":10,"address":"","mp_id":"","mp_lat":"-31.93418231","mp_lng":"115.84162131","created_at":"2020-11-06T02:07:04.000000Z","updated_at":"2020-11-06T02:07:04.000000Z","upload_id":null,"floor_id":4},"78":{"id":78,"name":"A125","type":2,"parent_id":10,"address":"","mp_id":"","mp_lat":"-31.93418893","mp_lng":"115.84169543","created_at":"2020-11-06T02:10:52.000000Z","updated_at":"2020-11-06T02:10:52.000000Z","upload_id":null,"floor_id":4},"79":{"id":79,"name":"A137","type":2,"parent_id":10,"address":"","mp_id":"","mp_lat":"-31.93415144","mp_lng":"115.84192825","created_at":"2020-11-06T02:12:50.000000Z","updated_at":"2020-11-06T02:12:50.000000Z","upload_id":null,"floor_id":4},"80":{"id":80,"name":"A139","type":2,"parent_id":10,"address":"","mp_id":"","mp_lat":"-31.93415151","mp_lng":"115.84206042","created_at":"2020-11-06T02:14:12.000000Z","updated_at":"2020-11-06T02:14:12.000000Z","upload_id":null,"floor_id":4},"81":{"id":81,"name":"A141","type":2,"parent_id":10,"address":"","mp_id":"","mp_lat":"-31.93415245","mp_lng":"115.84224336","created_at":"2020-11-06T02:18:39.000000Z","updated_at":"2020-11-06T02:18:39.000000Z","upload_id":null,"floor_id":4},"82":{"id":82,"name":"A150","type":2,"parent_id":10,"address":"","mp_id":"","mp_lat":"-31.93415736","mp_lng":"115.84263034","created_at":"2020-11-06T02:20:41.000000Z","updated_at":"2020-11-06T02:20:41.000000Z","upload_id":null,"floor_id":4},"83":{"id":83,"name":"A151","type":2,"parent_id":10,"address":"","mp_id":"","mp_lat":"-31.93416074","mp_lng":"115.84270302","created_at":"2020-11-06T02:24:19.000000Z","updated_at":"2020-11-06T02:24:19.000000Z","upload_id":null,"floor_id":4},"84":{"id":84,"name":"A152","type":2,"parent_id":10,"address":"","mp_id":"","mp_lat":"-31.93415859","mp_lng":"115.84277524","created_at":"2020-11-06T02:25:42.000000Z","updated_at":"2020-11-06T02:25:42.000000Z","upload_id":null,"floor_id":4},"85":{"id":85,"name":"A153","type":2,"parent_id":10,"address":"","mp_id":"","mp_lat":"-31.93415866","mp_lng":"115.84285291","created_at":"2020-11-06T02:27:00.000000Z","updated_at":"2020-11-06T02:27:00.000000Z","upload_id":null,"floor_id":4},"86":{"id":86,"name":"A154","type":2,"parent_id":10,"address":"","mp_id":"","mp_lat":"-31.93416138","mp_lng":"115.84292221","created_at":"2020-11-06T02:28:29.000000Z","updated_at":"2020-11-06T02:28:29.000000Z","upload_id":null,"floor_id":4},"87":{"id":87,"name":"A221","type":2,"parent_id":10,"address":"","mp_id":"","mp_lat":"-31.93376091","mp_lng":"115.84290092","created_at":"2020-11-06T02:31:07.000000Z","updated_at":"2020-11-06T02:31:07.000000Z","upload_id":null,"floor_id":5},"88":{"id":88,"name":"A232","type":2,"parent_id":10,"address":"","mp_id":"","mp_lat":"-31.93384341","mp_lng":"115.84228616","created_at":"2020-11-06T02:32:54.000000Z","updated_at":"2020-11-06T02:32:54.000000Z","upload_id":null,"floor_id":5},"89":{"id":89,"name":"A233","type":2,"parent_id":10,"address":"","mp_id":"","mp_lat":"-31.93384571","mp_lng":"115.84220592","created_at":"2020-11-06T02:34:13.000000Z","updated_at":"2020-11-06T02:34:13.000000Z","upload_id":null,"floor_id":5},"90":{"id":90,"name":"A234","type":2,"parent_id":10,"address":"","mp_id":"","mp_lat":"-31.93384407","mp_lng":"115.84212101","created_at":"2020-11-06T02:36:43.000000Z","updated_at":"2020-11-06T02:36:43.000000Z","upload_id":null,"floor_id":5},"91":{"id":91,"name":"A235","type":2,"parent_id":10,"address":"","mp_id":"","mp_lat":"-31.93384478","mp_lng":"115.84203646","created_at":"2020-11-06T02:38:15.000000Z","updated_at":"2020-11-06T02:38:15.000000Z","upload_id":null,"floor_id":5},"92":{"id":92,"name":"A236","type":2,"parent_id":10,"address":"","mp_id":"","mp_lat":"-31.93384200","mp_lng":"115.84195445","created_at":"2020-11-06T02:39:39.000000Z","updated_at":"2020-11-06T02:39:39.000000Z","upload_id":null,"floor_id":5},"93":{"id":93,"name":"A237","type":2,"parent_id":10,"address":"","mp_id":"","mp_lat":"-31.93371228","mp_lng":"115.84193860","created_at":"2020-11-06T02:40:59.000000Z","updated_at":"2020-11-06T02:40:59.000000Z","upload_id":null,"floor_id":5},"94":{"id":94,"name":"A239","type":2,"parent_id":10,"address":"","mp_id":"","mp_lat":"-31.93371018","mp_lng":"115.84187253","created_at":"2020-11-06T02:42:08.000000Z","updated_at":"2020-11-06T02:42:08.000000Z","upload_id":null,"floor_id":5},"95":{"id":95,"name":"A241","type":2,"parent_id":10,"address":"","mp_id":"","mp_lat":"-31.93368682","mp_lng":"115.84176706","created_at":"2020-11-06T02:43:26.000000Z","updated_at":"2020-11-06T02:43:26.000000Z","upload_id":null,"floor_id":5},"96":{"id":96,"name":"A242","type":2,"parent_id":10,"address":"","mp_id":"","mp_lat":"-31.93368895","mp_lng":"115.84181844","created_at":"2020-11-06T02:47:26.000000Z","updated_at":"2020-11-06T02:47:26.000000Z","upload_id":null,"floor_id":5},"97":{"id":97,"name":"A261","type":2,"parent_id":10,"address":"","mp_id":"","mp_lat":"-31.93400965","mp_lng":"115.84239065","created_at":"2020-11-06T02:48:39.000000Z","updated_at":"2020-11-06T02:48:39.000000Z","upload_id":null,"floor_id":5},"98":{"id":98,"name":"A274","type":2,"parent_id":10,"address":"","mp_id":"","mp_lat":"-31.93415607","mp_lng":"115.84248878","created_at":"2020-11-06T02:49:39.000000Z","updated_at":"2020-11-06T02:49:39.000000Z","upload_id":null,"floor_id":5},"99":{"id":99,"name":"A275","type":2,"parent_id":10,"address":"","mp_id":"","mp_lat":"-31.93415776","mp_lng":"115.84263678","created_at":"2020-11-06T02:50:53.000000Z","updated_at":"2020-11-06T02:50:53.000000Z","upload_id":null,"floor_id":5},"100":{"id":100,"name":"A276","type":2,"parent_id":10,"address":"","mp_id":"","mp_lat":"-31.93415888","mp_lng":"115.84274945","created_at":"2020-11-06T02:52:28.000000Z","updated_at":"2020-11-06T02:52:28.000000Z","upload_id":null,"floor_id":5},"101":{"id":101,"name":"A277","type":2,"parent_id":10,"address":"","mp_id":"","mp_lat":"-31.93415941","mp_lng":"115.84290165","created_at":"2020-11-06T02:56:19.000000Z","updated_at":"2020-11-06T02:56:19.000000Z","upload_id":null,"floor_id":5},"102":{"id":102,"name":"A301","type":2,"parent_id":10,"address":"","mp_id":"","mp_lat":"-31.93369543","mp_lng":"115.84238469","created_at":"2020-11-06T02:57:55.000000Z","updated_at":"2020-11-06T02:57:55.000000Z","upload_id":null,"floor_id":6},"103":{"id":103,"name":"A304","type":2,"parent_id":10,"address":"","mp_id":"","mp_lat":"-31.93385172","mp_lng":"115.84239308","created_at":"2020-11-06T02:58:52.000000Z","updated_at":"2020-11-06T02:58:52.000000Z","upload_id":null,"floor_id":6},"104":{"id":104,"name":"A305","type":2,"parent_id":10,"address":"","mp_id":"","mp_lat":"-31.93384402","mp_lng":"115.84229283","created_at":"2020-11-06T02:59:51.000000Z","updated_at":"2020-11-06T02:59:51.000000Z","upload_id":null,"floor_id":6},"105":{"id":105,"name":"A306","type":2,"parent_id":10,"address":"","mp_id":"","mp_lat":"-31.93384348","mp_lng":"115.84220477","created_at":"2020-11-06T03:00:39.000000Z","updated_at":"2020-11-06T03:00:39.000000Z","upload_id":null,"floor_id":6},"106":{"id":106,"name":"A307","type":2,"parent_id":10,"address":"","mp_id":"","mp_lat":"-31.93384186","mp_lng":"115.84212437","created_at":"2020-11-06T03:01:33.000000Z","updated_at":"2020-11-06T03:01:33.000000Z","upload_id":null,"floor_id":6},"107":{"id":107,"name":"A308","type":2,"parent_id":10,"address":"","mp_id":"","mp_lat":"-31.93384040","mp_lng":"115.84204656","created_at":"2020-11-06T03:02:31.000000Z","updated_at":"2020-11-06T03:02:31.000000Z","upload_id":null,"floor_id":6},"108":{"id":108,"name":"A310","type":2,"parent_id":10,"address":"","mp_id":"","mp_lat":"-31.93384073","mp_lng":"115.84195403","created_at":"2020-11-06T03:03:51.000000Z","updated_at":"2020-11-06T03:03:51.000000Z","upload_id":null,"floor_id":6},"109":{"id":109,"name":"A312","type":2,"parent_id":10,"address":"","mp_id":"","mp_lat":"-31.93375080","mp_lng":"115.84205159","created_at":"2020-11-06T03:05:33.000000Z","updated_at":"2020-11-06T03:05:33.000000Z","upload_id":null,"floor_id":6},"110":{"id":110,"name":"A313","type":2,"parent_id":10,"address":"","mp_id":"","mp_lat":"-31.93372735","mp_lng":"115.84198117","created_at":"2020-11-06T03:06:49.000000Z","updated_at":"2020-11-06T03:06:49.000000Z","upload_id":null,"floor_id":6},"111":{"id":111,"name":"A314","type":2,"parent_id":10,"address":"","mp_id":"","mp_lat":"-31.93371157","mp_lng":"115.84188801","created_at":"2020-11-06T03:07:58.000000Z","updated_at":"2020-11-06T03:07:58.000000Z","upload_id":null,"floor_id":6},"112":{"id":112,"name":"A315","type":2,"parent_id":10,"address":"","mp_id":"","mp_lat":"-31.93369910","mp_lng":"115.84180293","created_at":"2020-11-06T03:09:22.000000Z","updated_at":"2020-11-06T03:09:22.000000Z","upload_id":null,"floor_id":6},"113":{"id":113,"name":"A316","type":2,"parent_id":10,"address":"","mp_id":"","mp_lat":"-31.93368912","mp_lng":"115.84174585","created_at":"2020-11-06T03:10:55.000000Z","updated_at":"2020-11-06T03:10:55.000000Z","upload_id":null,"floor_id":6},"114":{"id":114,"name":"A317","type":2,"parent_id":10,"address":"","mp_id":"","mp_lat":"-31.93370886","mp_lng":"115.84164288","created_at":"2020-11-06T03:12:20.000000Z","updated_at":"2020-11-06T03:12:20.000000Z","upload_id":null,"floor_id":6},"115":{"id":115,"name":"A318","type":2,"parent_id":10,"address":"","mp_id":"","mp_lat":"-31.93376047","mp_lng":"115.84172046","created_at":"2020-11-06T03:13:32.000000Z","updated_at":"2020-11-06T03:13:32.000000Z","upload_id":null,"floor_id":6},"116":{"id":116,"name":"A321","type":2,"parent_id":10,"address":"","mp_id":"","mp_lat":"-31.93381530","mp_lng":"115.84181089","created_at":"2020-11-06T03:14:32.000000Z","updated_at":"2020-11-06T03:14:32.000000Z","upload_id":null,"floor_id":6},"117":{"id":117,"name":"A331","type":2,"parent_id":10,"address":"","mp_id":"","mp_lat":"-31.93408196","mp_lng":"115.84170654","created_at":"2020-11-06T03:16:10.000000Z","updated_at":"2020-11-06T03:16:10.000000Z","upload_id":null,"floor_id":6},"118":{"id":118,"name":"A332","type":2,"parent_id":10,"address":"","mp_id":"","mp_lat":"-31.93409220","mp_lng":"115.84161561","created_at":"2020-11-06T03:18:16.000000Z","updated_at":"2020-11-06T03:18:16.000000Z","upload_id":null,"floor_id":6},"119":{"id":119,"name":"A337","type":2,"parent_id":10,"address":"","mp_id":"","mp_lat":"-31.93420797","mp_lng":"115.84182579","created_at":"2020-11-06T03:20:50.000000Z","updated_at":"2020-11-06T03:20:50.000000Z","upload_id":null,"floor_id":6},"120":{"id":120,"name":"A338","type":2,"parent_id":10,"address":"","mp_id":"","mp_lat":"-31.93416673","mp_lng":"115.84182197","created_at":"2020-11-06T03:21:48.000000Z","updated_at":"2020-11-06T03:21:48.000000Z","upload_id":null,"floor_id":6},"121":{"id":121,"name":"A342","type":2,"parent_id":10,"address":"","mp_id":"","mp_lat":"-31.93414877","mp_lng":"115.84193614","created_at":"2020-11-06T03:22:54.000000Z","updated_at":"2020-11-06T03:22:54.000000Z","upload_id":null,"floor_id":6},"122":{"id":122,"name":"A344","type":2,"parent_id":10,"address":"","mp_id":"","mp_lat":"-31.93415300","mp_lng":"115.84207891","created_at":"2020-11-06T03:23:54.000000Z","updated_at":"2020-11-06T03:23:54.000000Z","upload_id":null,"floor_id":6},"123":{"id":123,"name":"A401","type":2,"parent_id":10,"address":"","mp_id":"","mp_lat":"-31.93379763","mp_lng":"115.84182818","created_at":"2020-11-06T03:24:51.000000Z","updated_at":"2020-11-06T03:24:51.000000Z","upload_id":null,"floor_id":7},"124":{"id":124,"name":"A412","type":2,"parent_id":10,"address":"","mp_id":"","mp_lat":"-31.93408866","mp_lng":"115.84164153","created_at":"2020-11-06T03:25:40.000000Z","updated_at":"2020-11-06T03:25:40.000000Z","upload_id":null,"floor_id":7},"125":{"id":125,"name":"A414","type":2,"parent_id":10,"address":"","mp_id":"","mp_lat":"-31.93417795","mp_lng":"115.84164499","created_at":"2020-11-06T03:26:36.000000Z","updated_at":"2020-11-06T03:26:36.000000Z","upload_id":null,"floor_id":7},"126":{"id":126,"name":"1-08","type":2,"parent_id":3,"address":"","mp_id":"","mp_lat":"-31.94702243","mp_lng":"115.86075273","created_at":"2020-11-06T03:32:24.000000Z","updated_at":"2020-11-06T03:32:24.000000Z","upload_id":null,"floor_id":1},"127":{"id":127,"name":"1-14","type":2,"parent_id":3,"address":"","mp_id":"","mp_lat":"-31.94690673","mp_lng":"115.86093776","created_at":"2020-11-06T03:33:14.000000Z","updated_at":"2020-11-06T03:33:14.000000Z","upload_id":null,"floor_id":1},"128":{"id":128,"name":"1-06","type":2,"parent_id":3,"address":"","mp_id":"","mp_lat":"-31.94706336","mp_lng":"115.86083156","created_at":"2020-11-06T03:34:18.000000Z","updated_at":"2020-11-06T03:34:18.000000Z","upload_id":null,"floor_id":1},"129":{"id":129,"name":"1-05","type":2,"parent_id":3,"address":"","mp_id":"","mp_lat":"-31.94712036","mp_lng":"115.86080256","created_at":"2020-11-06T03:35:09.000000Z","updated_at":"2020-11-06T03:35:09.000000Z","upload_id":null,"floor_id":1},"130":{"id":130,"name":"1-16","type":2,"parent_id":3,"address":"","mp_id":"","mp_lat":"-31.94697613","mp_lng":"115.86103776","created_at":"2020-11-06T03:36:07.000000Z","updated_at":"2020-11-06T03:36:07.000000Z","upload_id":null,"floor_id":1},"131":{"id":131,"name":"1-25","type":2,"parent_id":3,"address":"","mp_id":"","mp_lat":"-31.94713526","mp_lng":"115.86095356","created_at":"2020-11-06T03:37:45.000000Z","updated_at":"2020-11-06T03:37:45.000000Z","upload_id":null,"floor_id":1},"132":{"id":132,"name":"1-26","type":2,"parent_id":3,"address":"","mp_id":"","mp_lat":"-31.94719255","mp_lng":"115.86091342","created_at":"2020-11-06T03:38:37.000000Z","updated_at":"2020-11-06T03:38:37.000000Z","upload_id":null,"floor_id":1},"133":{"id":133,"name":"1-28","type":2,"parent_id":3,"address":"","mp_id":"","mp_lat":"-31.94707970","mp_lng":"115.86110380","created_at":"2020-11-06T03:39:45.000000Z","updated_at":"2020-11-06T03:39:45.000000Z","upload_id":null,"floor_id":1},"134":{"id":134,"name":"1-29","type":2,"parent_id":3,"address":"","mp_id":"","mp_lat":"-31.94701694","mp_lng":"115.86122596","created_at":"2020-11-06T03:40:45.000000Z","updated_at":"2020-11-06T03:40:45.000000Z","upload_id":null,"floor_id":1},"135":{"id":135,"name":"1-30","type":2,"parent_id":3,"address":"","mp_id":"","mp_lat":"-31.94707961","mp_lng":"115.86120802","created_at":"2020-11-06T03:41:38.000000Z","updated_at":"2020-11-06T03:41:38.000000Z","upload_id":null,"floor_id":1},"136":{"id":136,"name":"1-33","type":2,"parent_id":3,"address":"","mp_id":"","mp_lat":"-31.94718558","mp_lng":"115.86113096","created_at":"2020-11-06T03:42:49.000000Z","updated_at":"2020-11-06T03:42:49.000000Z","upload_id":null,"floor_id":1},"137":{"id":137,"name":"1-34","type":2,"parent_id":3,"address":"","mp_id":"","mp_lat":"-31.94724407","mp_lng":"115.86112403","created_at":"2020-11-06T03:43:56.000000Z","updated_at":"2020-11-06T03:43:56.000000Z","upload_id":null,"floor_id":1},"138":{"id":138,"name":"1-27","type":2,"parent_id":3,"address":"","mp_id":"","mp_lat":"-31.94730872","mp_lng":"115.86100647","created_at":"2020-11-06T03:44:57.000000Z","updated_at":"2020-11-06T03:44:57.000000Z","upload_id":null,"floor_id":1},"139":{"id":139,"name":"1-35","type":2,"parent_id":3,"address":"","mp_id":"","mp_lat":"-31.94731576","mp_lng":"115.86108246","created_at":"2020-11-06T03:45:55.000000Z","updated_at":"2020-11-06T03:45:55.000000Z","upload_id":null,"floor_id":1},"140":{"id":140,"name":"2-85","type":2,"parent_id":3,"address":"","mp_id":"","mp_lat":"-31.94745710","mp_lng":"115.86129405","created_at":"2020-11-06T03:47:51.000000Z","updated_at":"2020-11-06T03:47:51.000000Z","upload_id":null,"floor_id":2},"141":{"id":141,"name":"2-13","type":2,"parent_id":3,"address":"","mp_id":"","mp_lat":"-31.94729478","mp_lng":"115.86177044","created_at":"2020-11-06T03:48:44.000000Z","updated_at":"2020-11-06T03:48:44.000000Z","upload_id":null,"floor_id":2},"142":{"id":142,"name":"2-14","type":2,"parent_id":3,"address":"","mp_id":"","mp_lat":"-31.94733216","mp_lng":"115.86172278","created_at":"2020-11-06T03:49:31.000000Z","updated_at":"2020-11-06T03:49:31.000000Z","upload_id":null,"floor_id":2},"143":{"id":143,"name":"3-10","type":2,"parent_id":3,"address":"","mp_id":"","mp_lat":"-31.94714128","mp_lng":"115.86130725","created_at":"2020-11-06T03:55:22.000000Z","updated_at":"2020-11-06T03:55:22.000000Z","upload_id":null,"floor_id":3},"144":{"id":144,"name":"3-11","type":2,"parent_id":3,"address":"","mp_id":"","mp_lat":"-31.94710036","mp_lng":"115.86118585","created_at":"2020-11-06T03:56:04.000000Z","updated_at":"2020-11-06T03:56:04.000000Z","upload_id":null,"floor_id":3},"145":{"id":145,"name":"3-12","type":2,"parent_id":3,"address":"","mp_id":"","mp_lat":"-31.94705708","mp_lng":"115.86108245","created_at":"2020-11-06T03:57:51.000000Z","updated_at":"2020-11-06T03:57:51.000000Z","upload_id":null,"floor_id":3},"146":{"id":146,"name":"3-13","type":2,"parent_id":3,"address":"","mp_id":"","mp_lat":"-31.94702144","mp_lng":"115.86099174","created_at":"2020-11-06T03:58:41.000000Z","updated_at":"2020-11-06T03:58:41.000000Z","upload_id":null,"floor_id":3},"147":{"id":147,"name":"3-14","type":2,"parent_id":3,"address":"","mp_id":"","mp_lat":"-31.94696660","mp_lng":"115.86082481","created_at":"2020-11-06T03:59:46.000000Z","updated_at":"2020-11-06T03:59:46.000000Z","upload_id":null,"floor_id":3},"148":{"id":148,"name":"3-15","type":2,"parent_id":3,"address":"","mp_id":"","mp_lat":"-31.94709628","mp_lng":"115.86080537","created_at":"2020-11-06T04:00:26.000000Z","updated_at":"2020-11-06T04:00:26.000000Z","upload_id":null,"floor_id":3},"149":{"id":149,"name":"3-02","type":2,"parent_id":3,"address":"","mp_id":"","mp_lat":"-31.94737778","mp_lng":"115.86111818","created_at":"2020-11-06T04:01:52.000000Z","updated_at":"2020-11-06T04:01:52.000000Z","upload_id":null,"floor_id":3},"150":{"id":150,"name":"3-03","type":2,"parent_id":3,"address":"","mp_id":"","mp_lat":"-31.94733791","mp_lng":"115.86102615","created_at":"2020-11-06T04:02:50.000000Z","updated_at":"2020-11-06T04:02:50.000000Z","upload_id":null,"floor_id":3},"151":{"id":151,"name":"3-05","type":2,"parent_id":3,"address":"","mp_id":"","mp_lat":"-31.94728606","mp_lng":"115.86093671","created_at":"2020-11-06T04:03:47.000000Z","updated_at":"2020-11-06T04:03:47.000000Z","upload_id":null,"floor_id":3},"152":{"id":152,"name":"3-07","type":2,"parent_id":3,"address":"","mp_id":"","mp_lat":"-31.94724140","mp_lng":"115.86084822","created_at":"2020-11-06T04:04:58.000000Z","updated_at":"2020-11-06T04:04:58.000000Z","upload_id":null,"floor_id":3},"153":{"id":153,"name":"3-08","type":2,"parent_id":3,"address":"","mp_id":"","mp_lat":"-31.94719944","mp_lng":"115.86077512","created_at":"2020-11-06T04:06:24.000000Z","updated_at":"2020-11-06T04:06:24.000000Z","upload_id":null,"floor_id":3},"154":{"id":154,"name":"3-09","type":2,"parent_id":3,"address":"","mp_id":"","mp_lat":"-31.94715812","mp_lng":"115.86090891","created_at":"2020-11-06T04:07:14.000000Z","updated_at":"2020-11-06T04:07:14.000000Z","upload_id":null,"floor_id":3},"155":{"id":155,"name":"3-54","type":2,"parent_id":3,"address":"","mp_id":"","mp_lat":"-31.94731841","mp_lng":"115.86128842","created_at":"2020-11-06T04:08:14.000000Z","updated_at":"2020-11-06T04:08:14.000000Z","upload_id":null,"floor_id":3},"156":{"id":156,"name":"A101","type":2,"parent_id":10,"address":"","mp_id":"","mp_lat":"-31.93383901","mp_lng":"115.84223426","created_at":null,"updated_at":null,"upload_id":null,"floor_id":4},"157":{"id":157,"name":"A101B","type":2,"parent_id":10,"address":"","mp_id":"","mp_lat":"-31.93384972","mp_lng":"115.84214611","created_at":null,"updated_at":null,"upload_id":null,"floor_id":4},"158":{"id":158,"name":"A101D","type":2,"parent_id":10,"address":"","mp_id":"","mp_lat":"-31.93385371","mp_lng":"115.84206667","created_at":null,"updated_at":null,"upload_id":null,"floor_id":4},"159":{"id":159,"name":"A101E","type":2,"parent_id":10,"address":"","mp_id":"","mp_lat":"-31.93385125","mp_lng":"115.84199585","created_at":null,"updated_at":null,"upload_id":null,"floor_id":4},"160":{"id":160,"name":"A106","type":2,"parent_id":10,"address":"","mp_id":"","mp_lat":"-31.93384961","mp_lng":"115.84195786","created_at":null,"updated_at":null,"upload_id":null,"floor_id":4},"161":{"id":161,"name":"A123","type":2,"parent_id":10,"address":"","mp_id":"","mp_lat":"-31.93409869","mp_lng":"115.84161245","created_at":null,"updated_at":null,"upload_id":null,"floor_id":4},"162":{"id":162,"name":"A124","type":2,"parent_id":10,"address":"","mp_id":"","mp_lat":"-31.93418231","mp_lng":"115.84162131","created_at":null,"updated_at":null,"upload_id":null,"floor_id":4},"163":{"id":163,"name":"A125","type":2,"parent_id":10,"address":"","mp_id":"","mp_lat":"-31.93418893","mp_lng":"115.84169543","created_at":null,"updated_at":null,"upload_id":null,"floor_id":4},"164":{"id":164,"name":"A137","type":2,"parent_id":10,"address":"","mp_id":"","mp_lat":"-31.93415144","mp_lng":"115.84192825","created_at":null,"updated_at":null,"upload_id":null,"floor_id":4},"165":{"id":165,"name":"A139","type":2,"parent_id":10,"address":"","mp_id":"","mp_lat":"-31.93415151","mp_lng":"115.84206042","created_at":null,"updated_at":null,"upload_id":null,"floor_id":4},"166":{"id":166,"name":"A141","type":2,"parent_id":10,"address":"","mp_id":"","mp_lat":"-31.93415245","mp_lng":"115.84224336","created_at":null,"updated_at":null,"upload_id":null,"floor_id":4},"167":{"id":167,"name":"A150","type":2,"parent_id":10,"address":"","mp_id":"","mp_lat":"-31.93415736","mp_lng":"115.84263034","created_at":null,"updated_at":null,"upload_id":null,"floor_id":4},"168":{"id":168,"name":"A151","type":2,"parent_id":10,"address":"","mp_id":"","mp_lat":"-31.93416074","mp_lng":"115.84270302","created_at":null,"updated_at":null,"upload_id":null,"floor_id":4},"169":{"id":169,"name":"A152","type":2,"parent_id":10,"address":"","mp_id":"","mp_lat":"-31.93415859","mp_lng":"115.84277524","created_at":null,"updated_at":null,"upload_id":null,"floor_id":4},"170":{"id":170,"name":"A153","type":2,"parent_id":10,"address":"","mp_id":"","mp_lat":"-31.93415866","mp_lng":"115.84285291","created_at":null,"updated_at":null,"upload_id":null,"floor_id":4},"171":{"id":171,"name":"A154","type":2,"parent_id":10,"address":"","mp_id":"","mp_lat":"-31.93416138","mp_lng":"115.84292221","created_at":null,"updated_at":null,"upload_id":null,"floor_id":4},"172":{"id":172,"name":"A221","type":2,"parent_id":10,"address":"","mp_id":"","mp_lat":"-31.93376091","mp_lng":"115.84290092","created_at":null,"updated_at":null,"upload_id":null,"floor_id":5},"173":{"id":173,"name":"A232","type":2,"parent_id":10,"address":"","mp_id":"","mp_lat":"-31.93384341","mp_lng":"115.84228616","created_at":null,"updated_at":null,"upload_id":null,"floor_id":5},"174":{"id":174,"name":"A233","type":2,"parent_id":10,"address":"","mp_id":"","mp_lat":"-31.93384571","mp_lng":"115.84220592","created_at":null,"updated_at":null,"upload_id":null,"floor_id":5},"175":{"id":175,"name":"A234","type":2,"parent_id":10,"address":"","mp_id":"","mp_lat":"-31.93384407","mp_lng":"115.84212101","created_at":null,"updated_at":null,"upload_id":null,"floor_id":5},"176":{"id":176,"name":"A235","type":2,"parent_id":10,"address":"","mp_id":"","mp_lat":"-31.93384478","mp_lng":"115.84203646","created_at":null,"updated_at":null,"upload_id":null,"floor_id":5},"177":{"id":177,"name":"A236","type":2,"parent_id":10,"address":"","mp_id":"","mp_lat":"-31.93384200","mp_lng":"115.84195445","created_at":null,"updated_at":null,"upload_id":null,"floor_id":5},"178":{"id":178,"name":"A237","type":2,"parent_id":10,"address":"","mp_id":"","mp_lat":"-31.93371228","mp_lng":"115.84193860","created_at":null,"updated_at":null,"upload_id":null,"floor_id":5},"179":{"id":179,"name":"A239","type":2,"parent_id":10,"address":"","mp_id":"","mp_lat":"-31.93371018","mp_lng":"115.84187253","created_at":null,"updated_at":null,"upload_id":null,"floor_id":5},"180":{"id":180,"name":"A241","type":2,"parent_id":10,"address":"","mp_id":"","mp_lat":"-31.93368682","mp_lng":"115.84176706","created_at":null,"updated_at":null,"upload_id":null,"floor_id":5},"181":{"id":181,"name":"A242","type":2,"parent_id":10,"address":"","mp_id":"","mp_lat":"-31.93368895","mp_lng":"115.84181844","created_at":null,"updated_at":null,"upload_id":null,"floor_id":5},"182":{"id":182,"name":"A261","type":2,"parent_id":10,"address":"","mp_id":"","mp_lat":"-31.93400965","mp_lng":"115.84239065","created_at":null,"updated_at":null,"upload_id":null,"floor_id":5},"183":{"id":183,"name":"A274","type":2,"parent_id":10,"address":"","mp_id":"","mp_lat":"-31.93415607","mp_lng":"115.84248878","created_at":null,"updated_at":null,"upload_id":null,"floor_id":5},"184":{"id":184,"name":"A275","type":2,"parent_id":10,"address":"","mp_id":"","mp_lat":"-31.93415776","mp_lng":"115.84263678","created_at":null,"updated_at":null,"upload_id":null,"floor_id":5},"185":{"id":185,"name":"A276","type":2,"parent_id":10,"address":"","mp_id":"","mp_lat":"-31.93415888","mp_lng":"115.84274945","created_at":null,"updated_at":null,"upload_id":null,"floor_id":5},"186":{"id":186,"name":"A277","type":2,"parent_id":10,"address":"","mp_id":"","mp_lat":"-31.93415941","mp_lng":"115.84290165","created_at":null,"updated_at":null,"upload_id":null,"floor_id":5},"187":{"id":187,"name":"A301","type":2,"parent_id":10,"address":"","mp_id":"","mp_lat":"-31.93369543","mp_lng":"115.84238469","created_at":null,"updated_at":null,"upload_id":null,"floor_id":6},"188":{"id":188,"name":"A304","type":2,"parent_id":10,"address":"","mp_id":"","mp_lat":"-31.93385172","mp_lng":"115.84239308","created_at":null,"updated_at":null,"upload_id":null,"floor_id":6},"189":{"id":189,"name":"A305","type":2,"parent_id":10,"address":"","mp_id":"","mp_lat":"-31.93384402","mp_lng":"115.84229283","created_at":null,"updated_at":null,"upload_id":null,"floor_id":6},"190":{"id":190,"name":"A306","type":2,"parent_id":10,"address":"","mp_id":"","mp_lat":"-31.93384348","mp_lng":"115.84220477","created_at":null,"updated_at":null,"upload_id":null,"floor_id":6},"191":{"id":191,"name":"A307","type":2,"parent_id":10,"address":"","mp_id":"","mp_lat":"-31.93384186","mp_lng":"115.84212437","created_at":null,"updated_at":null,"upload_id":null,"floor_id":6},"192":{"id":192,"name":"A308","type":2,"parent_id":10,"address":"","mp_id":"","mp_lat":"-31.93384040","mp_lng":"115.84204656","created_at":null,"updated_at":null,"upload_id":null,"floor_id":6},"193":{"id":193,"name":"A310","type":2,"parent_id":10,"address":"","mp_id":"","mp_lat":"-31.93384073","mp_lng":"115.84195403","created_at":null,"updated_at":null,"upload_id":null,"floor_id":6},"194":{"id":194,"name":"A312","type":2,"parent_id":10,"address":"","mp_id":"","mp_lat":"-31.93375080","mp_lng":"115.84205159","created_at":null,"updated_at":null,"upload_id":null,"floor_id":6},"195":{"id":195,"name":"A313","type":2,"parent_id":10,"address":"","mp_id":"","mp_lat":"-31.93372735","mp_lng":"115.84198117","created_at":null,"updated_at":null,"upload_id":null,"floor_id":6},"196":{"id":196,"name":"A314","type":2,"parent_id":10,"address":"","mp_id":"","mp_lat":"-31.93371157","mp_lng":"115.84188801","created_at":null,"updated_at":null,"upload_id":null,"floor_id":6},"197":{"id":197,"name":"A315","type":2,"parent_id":10,"address":"","mp_id":"","mp_lat":"-31.93369910","mp_lng":"115.84180293","created_at":null,"updated_at":null,"upload_id":null,"floor_id":6},"198":{"id":198,"name":"A316","type":2,"parent_id":10,"address":"","mp_id":"","mp_lat":"-31.93368912","mp_lng":"115.84174585","created_at":null,"updated_at":null,"upload_id":null,"floor_id":6},"199":{"id":199,"name":"A317","type":2,"parent_id":10,"address":"","mp_id":"","mp_lat":"-31.93370886","mp_lng":"115.84164288","created_at":null,"updated_at":null,"upload_id":null,"floor_id":6},"200":{"id":200,"name":"A318","type":2,"parent_id":10,"address":"","mp_id":"","mp_lat":"-31.93376047","mp_lng":"115.84172046","created_at":null,"updated_at":null,"upload_id":null,"floor_id":6},"201":{"id":201,"name":"A321","type":2,"parent_id":10,"address":"","mp_id":"","mp_lat":"-31.93381530","mp_lng":"115.84181089","created_at":null,"updated_at":null,"upload_id":null,"floor_id":6},"202":{"id":202,"name":"A331","type":2,"parent_id":10,"address":"","mp_id":"","mp_lat":"-31.93408196","mp_lng":"115.84170654","created_at":null,"updated_at":null,"upload_id":null,"floor_id":6},"203":{"id":203,"name":"A332","type":2,"parent_id":10,"address":"","mp_id":"","mp_lat":"-31.93409220","mp_lng":"115.84161561","created_at":null,"updated_at":null,"upload_id":null,"floor_id":6},"204":{"id":204,"name":"A337","type":2,"parent_id":10,"address":"","mp_id":"","mp_lat":"-31.93420797","mp_lng":"115.84182579","created_at":null,"updated_at":null,"upload_id":null,"floor_id":6},"205":{"id":205,"name":"A338","type":2,"parent_id":10,"address":"","mp_id":"","mp_lat":"-31.93416673","mp_lng":"115.84182197","created_at":null,"updated_at":null,"upload_id":null,"floor_id":6},"206":{"id":206,"name":"A342","type":2,"parent_id":10,"address":"","mp_id":"","mp_lat":"-31.93414877","mp_lng":"115.84193614","created_at":null,"updated_at":null,"upload_id":null,"floor_id":6},"207":{"id":207,"name":"A344","type":2,"parent_id":10,"address":"","mp_id":"","mp_lat":"-31.93415300","mp_lng":"115.84207891","created_at":null,"updated_at":null,"upload_id":null,"floor_id":6},"208":{"id":208,"name":"A401","type":2,"parent_id":10,"address":"","mp_id":"","mp_lat":"-31.93379763","mp_lng":"115.84182818","created_at":null,"updated_at":null,"upload_id":null,"floor_id":7},"209":{"id":209,"name":"A412","type":2,"parent_id":10,"address":"","mp_id":"","mp_lat":"-31.93408866","mp_lng":"115.84164153","created_at":null,"updated_at":null,"upload_id":null,"floor_id":7},"210":{"id":210,"name":"A414","type":2,"parent_id":10,"address":"","mp_id":"","mp_lat":"-31.93417795","mp_lng":"115.84164499","created_at":null,"updated_at":null,"upload_id":null,"floor_id":7},"211":{"id":211,"name":"1-08","type":2,"parent_id":3,"address":"","mp_id":"","mp_lat":"-31.94702243","mp_lng":"115.86075273","created_at":null,"updated_at":null,"upload_id":null,"floor_id":1},"212":{"id":212,"name":"1-14","type":2,"parent_id":3,"address":"","mp_id":"","mp_lat":"-31.94690673","mp_lng":"115.86093776","created_at":null,"updated_at":null,"upload_id":null,"floor_id":1},"213":{"id":213,"name":"1-06","type":2,"parent_id":3,"address":"","mp_id":"","mp_lat":"-31.94706336","mp_lng":"115.86083156","created_at":null,"updated_at":null,"upload_id":null,"floor_id":1},"214":{"id":214,"name":"1-05","type":2,"parent_id":3,"address":"","mp_id":"","mp_lat":"-31.94712036","mp_lng":"115.86080256","created_at":null,"updated_at":null,"upload_id":null,"floor_id":1},"215":{"id":215,"name":"1-16","type":2,"parent_id":3,"address":"","mp_id":"","mp_lat":"-31.94697613","mp_lng":"115.86103776","created_at":null,"updated_at":null,"upload_id":null,"floor_id":1},"216":{"id":216,"name":"1-25","type":2,"parent_id":3,"address":"","mp_id":"","mp_lat":"-31.94713526","mp_lng":"115.86095356","created_at":null,"updated_at":null,"upload_id":null,"floor_id":1},"217":{"id":217,"name":"1-26","type":2,"parent_id":3,"address":"","mp_id":"","mp_lat":"-31.94719255","mp_lng":"115.86091342","created_at":null,"updated_at":null,"upload_id":null,"floor_id":1},"218":{"id":218,"name":"1-28","type":2,"parent_id":3,"address":"","mp_id":"","mp_lat":"-31.94707970","mp_lng":"115.86110380","created_at":null,"updated_at":null,"upload_id":null,"floor_id":1},"219":{"id":219,"name":"1-29","type":2,"parent_id":3,"address":"","mp_id":"","mp_lat":"-31.94701694","mp_lng":"115.86122596","created_at":null,"updated_at":null,"upload_id":null,"floor_id":1},"220":{"id":220,"name":"1-30","type":2,"parent_id":3,"address":"","mp_id":"","mp_lat":"-31.94707961","mp_lng":"115.86120802","created_at":null,"updated_at":null,"upload_id":null,"floor_id":1},"221":{"id":221,"name":"1-33","type":2,"parent_id":3,"address":"","mp_id":"","mp_lat":"-31.94718558","mp_lng":"115.86113096","created_at":null,"updated_at":null,"upload_id":null,"floor_id":1},"222":{"id":222,"name":"1-34","type":2,"parent_id":3,"address":"","mp_id":"","mp_lat":"-31.94724407","mp_lng":"115.86112403","created_at":null,"updated_at":null,"upload_id":null,"floor_id":1},"223":{"id":223,"name":"1-27","type":2,"parent_id":3,"address":"","mp_id":"","mp_lat":"-31.94730872","mp_lng":"115.86100647","created_at":null,"updated_at":null,"upload_id":null,"floor_id":1},"224":{"id":224,"name":"1-35","type":2,"parent_id":3,"address":"","mp_id":"","mp_lat":"-31.94731576","mp_lng":"115.86108246","created_at":null,"updated_at":null,"upload_id":null,"floor_id":1},"225":{"id":225,"name":"2-85","type":2,"parent_id":3,"address":"","mp_id":"","mp_lat":"-31.94745710","mp_lng":"115.86129405","created_at":null,"updated_at":null,"upload_id":null,"floor_id":2},"226":{"id":226,"name":"2-13","type":2,"parent_id":3,"address":"","mp_id":"","mp_lat":"-31.94729478","mp_lng":"115.86177044","created_at":null,"updated_at":null,"upload_id":null,"floor_id":2},"227":{"id":227,"name":"2-14","type":2,"parent_id":3,"address":"","mp_id":"","mp_lat":"-31.94733216","mp_lng":"115.86172278","created_at":null,"updated_at":null,"upload_id":null,"floor_id":2},"228":{"id":228,"name":"3-10","type":2,"parent_id":3,"address":"","mp_id":"","mp_lat":"-31.94714128","mp_lng":"115.86130725","created_at":null,"updated_at":null,"upload_id":null,"floor_id":3},"229":{"id":229,"name":"3-11","type":2,"parent_id":3,"address":"","mp_id":"","mp_lat":"-31.94710036","mp_lng":"115.86118585","created_at":null,"updated_at":null,"upload_id":null,"floor_id":3},"230":{"id":230,"name":"3-12","type":2,"parent_id":3,"address":"","mp_id":"","mp_lat":"-31.94705708","mp_lng":"115.86108245","created_at":null,"updated_at":null,"upload_id":null,"floor_id":3},"231":{"id":231,"name":"3-13","type":2,"parent_id":3,"address":"","mp_id":"","mp_lat":"-31.94702144","mp_lng":"115.86099174","created_at":null,"updated_at":null,"upload_id":null,"floor_id":3},"232":{"id":232,"name":"3-14","type":2,"parent_id":3,"address":"","mp_id":"","mp_lat":"-31.94696660","mp_lng":"115.86082481","created_at":null,"updated_at":null,"upload_id":null,"floor_id":3},"233":{"id":233,"name":"3-15","type":2,"parent_id":3,"address":"","mp_id":"","mp_lat":"-31.94709628","mp_lng":"115.86080537","created_at":null,"updated_at":null,"upload_id":null,"floor_id":3},"234":{"id":234,"name":"3-02","type":2,"parent_id":3,"address":"","mp_id":"","mp_lat":"-31.94737778","mp_lng":"115.86111818","created_at":null,"updated_at":null,"upload_id":null,"floor_id":3},"235":{"id":235,"name":"3-03","type":2,"parent_id":3,"address":"","mp_id":"","mp_lat":"-31.94733791","mp_lng":"115.86102615","created_at":null,"updated_at":null,"upload_id":null,"floor_id":3},"236":{"id":236,"name":"3-05","type":2,"parent_id":3,"address":"","mp_id":"","mp_lat":"-31.94728606","mp_lng":"115.86093671","created_at":null,"updated_at":null,"upload_id":null,"floor_id":3},"237":{"id":237,"name":"3-07","type":2,"parent_id":3,"address":"","mp_id":"","mp_lat":"-31.94724140","mp_lng":"115.86084822","created_at":null,"updated_at":null,"upload_id":null,"floor_id":3},"238":{"id":238,"name":"3-08","type":2,"parent_id":3,"address":"","mp_id":"","mp_lat":"-31.94719944","mp_lng":"115.86077512","created_at":null,"updated_at":null,"upload_id":null,"floor_id":3},"239":{"id":239,"name":"3-09","type":2,"parent_id":3,"address":"","mp_id":"","mp_lat":"-31.94715812","mp_lng":"115.86090891","created_at":null,"updated_at":null,"upload_id":null,"floor_id":3},"240":{"id":240,"name":"3-54","type":2,"parent_id":3,"address":"","mp_id":"","mp_lat":"-31.94731841","mp_lng":"115.86128842","created_at":null,"updated_at":null,"upload_id":null,"floor_id":3}}